fivetran_provider/__init__.py
fivetran_provider/example_dags/__init__.py
fivetran_provider/example_dags/example_fivetran.py
fivetran_provider/example_dags/example_fivetran_bigquery.py
fivetran_provider/example_dags/example_fivetran_bqml.py
fivetran_provider/example_dags/example_fivetran_dbt.py
fivetran_provider/example_dags/example_fivetran_xcom.py
fivetran_provider/hooks/__init__.py
fivetran_provider/hooks/fivetran.py
fivetran_provider/operators/__init__.py
fivetran_provider/operators/fivetran.py
fivetran_provider/sensors/__init__.py
fivetran_provider/sensors/fivetran.py
tests/__init__.py
tests/hooks/__init__.py
tests/hooks/test_hooks.py
tests/operators/__init__.py
tests/operators/test_operators.py
tests/sensors/__init__.py
tests/sensors/test_sensors.py
airflow_provider_fivetran-1.1.4.dist-info/LICENSE.md
airflow_provider_fivetran-1.1.4.dist-info/METADATA
airflow_provider_fivetran-1.1.4.dist-info/WHEEL
airflow_provider_fivetran-1.1.4.dist-info/entry_points.txt
airflow_provider_fivetran-1.1.4.dist-info/top_level.txt
airflow_provider_fivetran-1.1.4.dist-info/RECORD
