Metadata-Version: 2.1
Name: airflow-provider-fivetran
Version: 1.1.4
Summary: A Fivetran provider for Apache Airflow
Home-page: https://github.com/fivetran/airflow-provider-fivetran
Author: Fivetran
Author-email: devrel@fivetran.com
License: Apache License 2.0
Project-URL: Bug Tracker, https://github.com/fivetran/airflow-provider-fivetran/issues
Classifier: License :: OSI Approved :: Apache Software License
Classifier: Programming Language :: Python :: 3
Classifier: Operating System :: OS Independent
Requires-Python: >=3.6
License-File: LICENSE.md
Requires-Dist: requests
Requires-Dist: apache-airflow (>=1.10)
